{
  "header": {
    "production": {
      "title": "Produkcja",
      "exportData": {
        "title": "Export danych",
        "description": "Generowanie pliku excel z danymi systemu skanowania."
      },
      "rework": {
        "title": "Rework",
        "description": "Oznaczanie partii jako rework - ponowne skanowanie."
      },
      "articleConfig": {
        "title": "Konfiguracja artykułów",
        "description": "Dodawanie i edycja artykułów w systmie skanowania DMC."
      }
    },
    "inventory": {
      "title": "Inwentaryzacja",
      "inventory": {
        "title": "Inwentaryzacja",
        "description": "Aplikacja wspierająca proces inwentaryzacji."
      },
      "inventoryApprove": {
        "title": "Zatwierdzanie inwentaryzacji",
        "description": "Narzędzie do potwierdzania zinwentaryzowanych pozycji."
      }
    }
  },
  "noAccess": "Nie posiadasz uprawnień do tej funkcji. Kliknij by wysłać zgłoszenie w celu ich nadania:",
  "noAccessTitle": "Brak uprawnień!",
  "noAccessMailSubject": "Nadanie uprawnień do: (wpisz nazwę funkcji)",
  "home": {
    "title": "Cześć!"
  },
  "exportData": {},
  "articleConfig": {
    "tabs": {
      "edit": "Edytuj",
      "add": "Dodaj"
    },
    "add": {
      "z": {
        "workplace": "Podaj 3 małe litery oraz 2 cyfry! (np. eol74)",
        "articleNumber": "Podaj 5 cyfr!",
        "articleName": "Minimum 10 znaków!",
        "boxesPerPallet": "Wprowadź liczbę całkowitą!",
        "dmc": "Minimum 10 znaków!",
        "dmcValidation": "Ciąg minimum 4 znaków zawartych w polu DMC!",
        "dmcSecondValidation": "Ciąg minimum 4 znaków zawartych w polu DMC, inny niż w polu \"Walidowana wartość DMC\"!",
        "piecesPerBox": "Wprowadź liczbę całkowitą!",
        "hydraProcess": "Wybierz proces!"
      },
      "cardTitle": "Dodaj artykuł",
      "cardDescription": "Uzupełnij wszystkie dane by dodać nowy artykuł.",
      "workplaceFormLabel": "Stanowisko",
      "articleNumberFormLabel": "Numer artykułu",
      "articleNameFormLabel": "Nazwa artykułu",
      "piecesPerBoxFormLabel": "Ilość sztuk w boxie",
      "palletFormLabel": "Etykiety zbiorcze na paletę",
      "boxesPerPalletFormLabel": "Ilość boxów na palecie",
      "dmcFormLabel": "DMC",
      "dmcFormDescription": "Pełna zawartość skanowanego kodu DMC",
      "dmcFirstValidationFormLabel": "Walidowana wartość DMC",
      "dmcFirstValidationFormDescription": "Stała zawartość kodu (np. numer artykułu klienta) - ciąg znaków który musi zawierać skanowany kod DMC",
      "secondValidationCheckboxFormLabel": "Walidacja dwóch ciągów znaków",
      "dmcSecondValidationFormLabel": "Druga walidowana wartość DMC",
      "dmcSecondValidationFormDescription": "Używaj tylko w przyadku gdy DMC zawiera dwa stałe ciągi znaków (początek i koniec)!",
      "fordCheckboxFormLabel": "Walidacja daty FORD",
      "bmwCheckboxFormLabel": "Walidacja daty BMW",
      "hydraProcessFormLabel": "Proces Hydra",
      "hydraProcessFormDescription": "Proeces HYDRA z którego pochodzi artykuł.",
      "hydraProcessSelectOption050": "050 - po kontroli ciśnieniowej EOL",
      "hydraProcessSelectOption090": "090 - Q3",
      "hydraProcessSelectPlaceholder": "Wybierz proces właściwy dla danego artykułu",
      "articleNoteFormLabel": "Notatka do artykułu",
      "articleNoteFormDescription": "Dodatkowe informacje o artykule (np. rodzaj pakowania, nazwa \"obiegowa\" itp.)"
    }
  },
  "dmcheck": {
    "articleSelection": {
      "cardTitle": "Wybierz artykuł",
      "noArticleConfigForWorkplaceTitle": "Brak konfiguracji!",
      "noArticleConfigForWorkplaceDescription": "Brak artykułów w konfiguracji dla stanowiska: "
    },
    "personLogin": {
      "cardTitle": "Logowanie",
      "personalNumberInputPlaceholder": "Numer personalny",
      "confirmButton": "Potwierdź",
      "loginButton": "Zaloguj",
      "loginError": "Błędny login lub hasło!"
    }
  }
}
